alphaquant_db/__init__.py
alphaquant_db/client.py
alphaquant_db/utils.py
alphaquant_db-1.0.9.dist-info/METADATA
alphaquant_db-1.0.9.dist-info/WHEEL
alphaquant_db-1.0.9.dist-info/top_level.txt
alphaquant_db-1.0.9.dist-info/RECORD
