Metadata-Version: 2.4
Name: alphaquant-db
Version: 1.0.9
Summary: Async MongoDB client using Motor for Alphaquant
Author-email: Shashank Gupta <developer@alphaco.ai>
License: MIT
Project-URL: Homepage, https://github.com/AlphaCoAI-Projects/dadar
Project-URL: Bug Reports, https://github.com/AlphaCoAI-Projects/dadar/issues
Project-URL: Source, https://github.com/AlphaCoAI-Projects/dadar
Keywords: mongodb,motor,async,database,pymongo
Requires-Python: >=3.8
Requires-Dist: motor>=3.7.1
Requires-Dist: pymongo>=4.5.0
Requires-Dist: python-dotenv>=1.0.0
Provides-Extra: dev
Requires-Dist: pytest>=7.0.0; extra == "dev"
Requires-Dist: pytest-asyncio>=0.21.0; extra == "dev"
Requires-Dist: black>=22.0.0; extra == "dev"
Requires-Dist: flake8>=4.0.0; extra == "dev"
Requires-Dist: mypy>=0.950; extra == "dev"
